py_pkg_jraza19/__init__.py
py_pkg_jraza19/py_pkg_jraza19.py
py_pkg_jraza19-0.1.0.dist-info/LICENSE
py_pkg_jraza19-0.1.0.dist-info/WHEEL
py_pkg_jraza19-0.1.0.dist-info/METADATA
py_pkg_jraza19-0.1.0.dist-info/RECORD
