Metadata-Version: 2.1
Name: py-pkg-jraza19
Version: 0.1.0
Summary: Python package that eases the pain of concatenating Pandas categoricals!
License: MIT
Author: Javairia Raza
Author-email: jr.jem19@gmail.com
Requires-Python: >=3.8,<4.0
Classifier: License :: OSI Approved :: MIT License
Classifier: Programming Language :: Python :: 3
Classifier: Programming Language :: Python :: 3.8
Classifier: Programming Language :: Python :: 3.9
Requires-Dist: pandas (>=1.2.2,<2.0.0)
